LICENSE
MANIFEST.in
README.rst
setup.py
version.log
requirements/base.in
requirements/tests.in
twiser/__init__.py
twiser/twiser.py
twiser.egg-info/PKG-INFO
twiser.egg-info/SOURCES.txt
twiser.egg-info/dependency_links.txt
twiser.egg-info/requires.txt
twiser.egg-info/top_level.txt