Metadata-Version: 2.1
Name: twiser
Version: 0.0.0
Summary: Advanced variance reduction methods.
Home-page: https://github.com/twitter/twiser/
Author: Ryan Turner
Author-email: rdturnermtl@github.com
License: Apache v2
Platform: any
Requires-Python: >=3.7
Provides-Extra: test
License-File: LICENSE
